{
  "current": {
    "button_border_radius": 0,
    "block_border_radius": "none",
    "heading_color": "#1a1818",
    "text_color": "#1a1818",
    "secondary_background": "#f5f5f5",
    "success_color": "#2e9e7b",
    "error_color": "#de2a2a",
    "header_background": "#ffffff",
    "header_text_color": "#1a1818",
    "footer_background": "#ffffff",
    "footer_text_color": "#1a1818",
    "primary_button_background": "rgba(0,0,0,0)",
    "secondary_button_background": "rgba(0,0,0,0)",
    "secondary_button_text_color": "#1a1818",
    "product_on_sale_accent": "#de2a2a",
    "product_custom_label_background": "#007cac",
    "product_custom_label_2_background": "#f06a22",
    "product_in_stock_text_color": "#2e9e7b",
    "product_low_stock_text_color": "#de2a2a",
    "heading_font": "zurich_extended_n8",
    "heading_font_size": "medium",
    "heading_text_transform": "uppercase",
    "text_font": "zurich_n4",
    "text_font_size": 17,
    "currency_code_enabled": false,
    "stagger_products_apparition": true,
    "stagger_blog_posts_apparition": false,
    "round_color_swatches": false,
    "color_swatch_config": "Adriatic Blue:Adriatic-blue.png \nAgate Green:Agate-Green.png \nAir Blue:air-blue.png \nAleutian:aleutian.png \nAlloy:alloy.png \nAlloy Euphoria:alloy-euphoria.png \nAlloy Hibiscus Lines:alloy-hibiscus-lines.png \nAlloy Tek:alloy-tek.png \nAllure:allure.png \nAmaranth:amaranth.png \nAmerican beauty:american-beauty.png \nAngel Blue:angel-blue.png \nAngel Wing:angel-wing.png \nAnthracite:Anthracite.png \nAnthracite Anthracite:anthracite-anthracite.png\nAnthracite Birds Of Paradise:anthracite-birds-of-paradise.png \nAnthracite Burnt:anthracite-burnt.png \nAnthracite Castlerock:anthracite-castlerock.png \nAnthracite Grunge Scales:anthracite-grunge-scales.png \nAnthracite High Seas:anthracite-high-seas.png\nAnthracite High Seas Hale:anthracite-high-seas-hale.png \nAnthracite High Seas Halftone:anthracite-high-seas-halftone.png\nAnthracite Nc24 Dark Blue Nc24:anthracite-nc24-dark-blue-nc24.png \nAnthracite Out Of Tropics:anthracite-out-of-tropics.png \nAnthracite Pops Of Palm:anthracite-pops-of-palm.png \nAnthracite Pops Of Palm Critter:anthracite-pops-of-palm-critter.png\nAnthracite United Mahi:anthracite-united-mahi.png \nAnthracite Woodland:anthracite-woodland.png\nApricot Wash:Apricot-Wash.png \nAquatic:aquatic.png \nAquatic Water:aquatic-water.png \nArcadia:Arcadia.png \nAruba Blue:Aruba-Blue.png \nAruba Blue Blurred Leaf Lines:aruba-blue-blurred-leaf-lines.png\nAruba Blue Brilliant White:aruba-blue-brilliant-white.png \nAruba Blue Leopard Lily:aruba-blue-leopard-lily.png\nAruba Blue Lotta Lines:aruba-blue-lotta-lines.png\nAruba Blue Macroflora:aruba-blue-macroflora.png \nAshley Blue:Ashley-Blue.png \nAsphalt:asphalt.png \nAssault:assault.png\nAshley Blue Sahara Sun: ashley-blue-sahara-sun.png\nAtlantis:atlantis.png \nAurora:aurora.png \nAutumn Blaze:autumn-blaze.png \nBaltic Sea:baltic-sea.png \nBass:bass.png \nBass Aop:bass-aop.png \nBering Sea:bering-sea.png \nBiking Red:biking-red.png \nBiking Red Anthracite:biking-red-anthracite.png \nBiking Red Stone Blue:Biking-Red-Stone-Blue.png \nBiscay Bay:biscay-bay.png \nBistro Green:Bistro-Green.png \nBittersweet:Bittersweet.png \nBlack Abyss:black-abyss.png \nBlack Goblin:black-goblin.png \nBlack Grunge:black-grunge.png \nBlack On White:black-on-white.png \nBlazing Yellow:blazing-yellow.png \nBlooming Dahlia:Blooming-Dahlia.png \nBlossom:Blossom.png \nBlue Camo:blue-camo.png \nBluefin Trevally:bluefin-trevally.png \nBlue Haze:Blue-Haze.png \nBlue Haze Blurred Leaf Lines:blue-haze-blurred-leaf-lines.png \nBlue Haze Cheetah Streaks Tonal:blue-haze-cheetah-streaks-tonal.png\nBlue Haze High Seas:blue-haze-high-seas.png\nBlue Haze Lotta Lines:blue-haze-lotta-lines.png \nBlue Haze Macroflora:blue-haze-macroflora.png \nBlue Haze Swell:blue-haze-swell.png \nBlue Haze Swell Lyons Blue M80:blue-haze-swell-lyons-blue-m80.png \nBlue Heaven:blue-heaven.png \nBlue Heaven Heather:blue-heaven-heather.png \nBlue Indigo:blue-indigo.png \nBlue Moon:blue-moon.png \nBlue Shadow:blue-shadow.png \nBlue Shadow Water:blue-shadow-water.png\nBlue Tint:blue-tint.png \nBlue Wing Teal:blue-wing-teal.png \nBlue wing Teal Grunge Scales:Blue-wing-Teal-Grunge-Scales.png \nBright Aqua: bright-aqua.png \nBright white:bright-white.png \nBrilliant White:brilliant-white.png \nBrilliant White Haze:brilliant-white-haze.png \nBrilliant White Lush:brilliant-white-lush.png \nBristol Blue:bristol-blue.png \nCactus Flower:cactus-flower.png \nCamellia:camellia.png \nCamellia Burnt:camellia-burnt.png \nCamellia Burnt Anthracite Burnt:camellia-burnt-anthracite-burnt.png \nCamellia Tek:camellia-tek.png \nCantaloupe:cantaloupe.png \nCaribbean Sea:caribbean-sea.png \nCastlerock:Castlerock.png \nCastlerock H2o Digi:castlerock-h2o-digi.png\nCastlerock High Seas:castlerock-high-seas.png \nCastlerock Pops Of Palm: castlerock-pops-of-palm.png\nCeramic:ceramic.png \nCeramic High Seas Glacier Gray Digi Seas:ceramic-high-seas-glacier-gray-digi-seas.png\nCeramic M80:ceramic-m80.png \nCeramic White Caps:ceramic-white-caps.png \nChambray Blue:Chambray-Blue.png \nCherry Tomato:cherry-tomato.png \nClassic Blue:Classic-Blue.png \nCloud Dancer:Cloud-Dancer.png \nCloud Dye: cloud-dye.png\nCloud Merona:cloud-merona.png \nCoastal Green:coastal-green.png \nCool:Cool.png \nCoral:coral.png \nCoral Grouper:coral-grouper.png \nCoral Grouper Aop:coral-grouper-aop.png \nCoral Pink:coral-pink.png \nCrabapple:crabapple.png \nCrown Blue:Crown-Blue.png \nCrystal Blue:crystal-blue.png \nCrystal Pink:crystal-pink.png \nDark Blue:dark-blue.png \nDark Blue Fish Critter:dark-blue-fish-critter.png \nDark Blue H2o Digi:dark-blue-h2o-digi.png\nDark Blue Haze:dark-blue-haze.png \nDark Blue High Seas:dark-blue-high-seas.png \nDark Blue Nc24:dark-blue-nc24.png \nDark Blue Shark Teeth:dark-blue-shark-teeth.png \nDark Blue Water Blocks:dark-blue-water-blocks.png \nDeep Blue Sea:deep-blue-sea.png \nDeep Teal Grunge Scales:deep-teal-grunge-scales.png \nDeep Sea: deep-sea.png\nDelft:delft.png \nDove:dove.png \nDress Blue:dress-blue.png \nDress Blues:dress-blues.png \nDress Blues Classic Blue:dress-blues-classic-blue.png \nDress Blues Euphoria:dress-blues-euphoria.png \nDress Blues Euphoria Dress Blue Firework Palms:dress-blues-euphoria-dress-blue-firework-palms.png \nDress Blues Fireworks Palms:dress-blues-firework-palms.png \nDress Blues Fish Water Blocks:dress-blues-fish-water-blocks.png\nDress Blues H2o Digi:dress-blues-h2o-digi.png\nDress Blues High Seas:dress-blues-high-seas.png \nDress Blues Hula:dress-blues-hula.png \nDress Blues Hula Blues:dress-blues-hula-blues.png \nDress Blues Nc24:dress-blues-nc24.png \nDress Blues Pops Of Palm:dress-blues-pops-of-palm.png \nDress Blues Sun Fade Pocket:dress-blues-sun-fade-pocket.png\nDress Blues United Mahi:dress-blues-united-mahi.png \nDress Blues United Mahi Anthracite United Mahi:dress-blues-united-mahi-anthracite-united-mahi.png \nDress Blues Woodland:dress-blues-woodland.png\nDress Blues Woodland Dress Blues H2o Digi:dress-blues-woodland-dress-blues-h2o-digi.png\nDune:dune.png \nDusty Blue:dusty-blue.png \nDusty Cedar:Dusty-Cedar.png \nDusty Pink:dusty-pink.png \nExtreme Bass:extreme-bass.png \nFjord Blue:fjord-blue.png \nFrosty Spruce:frosty-spruce.png \nGeorgia Peach: georgia-peach.png\nGlacier Gray:glacier-gray.png  \nGlacier Gray Asslt:glacier-gray-asslt.png \nGlacier Gray Bamboo:glacier-gray-bamboo.png \nGlacier Gray Castlerock:glacier-gray-castlerock.png \nGlacier Gray Faded:glacier-gray-faded.png \nGlacier Gray Faded Mahi:glacier-gray-faded-mahi.png \nGlacier Gray Faded Mahi Faded:glacier-gray-faded-mahi-faded.png \nGlacier Gray Heather:glacier-gray-heather.png \nGlacier Gray High Seas:glacier-gray-high-seas.png\nGlacier Gray Hight Seas:glacier-gray-hight-seas.png \nGlacier Gray Lotta Lines:glacier-gray-lotta-lines.png \nGlacier Gray Lush Tonal:glacier-gray-lush-tonal.png\nGlacier Gray Nc24:glacier-gray-nc24.png \nGlacier Gray Seagull Critter:glacier-gray-seagull-critter.png \nGlacier Gray Vertical Stripe:glacier-gray-vertical-stripe.png\nGlacier Gray White:glacier-gray-white.png \nGlacier Gray Whitecaps:glacier-gray-whitecaps.png \nGlacier Gray White Caps:glacier-gray-white-caps.png\nGleam:gleam.png \nGoblin Blue:goblin-blue.png \nGolden Haze:Golden-Haze.png \nGrape:grape.png \nGray Mist:gray-mist.png \nGreen:green.png \nGreen Briar:Green-Briar.png \nGrey Mist:grey-mist.png  \nGrey Mist Bonefish:grey-mist-bonefish.png \nGrey Mist Grunge:grey-mist-grunge.png \nGrey Mist Water:grey-mist-water.png \nGrey Teal:grey-teal.png \nGrey Wahoo:grey-wahoo.png \nHawaiian Ocean:hawaiian-ocean.png\nHawaiian Ocean Grunge:Hawaiian-Ocean-Grunge.png \nHawaiian Ocean Pops Of Palms Dots:hawaiian-ocean-pops-of-palms-dots.png\nHawaiian Ocean Striped Arm:hawaiian-ocean-striped-arm.png  \nHeritage Blue:heritage-blue.png \nHigh Pressure Blue:high-pressure-blue.png \nHigh Rise Grey:high-rise-grey.png \nHigh Rise Grey Grunge:high-rise-grey-grunge.png \nHigh Risk Red:high-risk-red.png \nHoney Suckle:Honey-Suckle.png \nHorizon Blue:Horizon-Blue.png \nHumus:Humus.png \nHumus Hawaiian Ocean:humus-hawaiian-ocean.png \nInca Gold:inca-gold.png \nInsignia Blue:insignia-blue.png \nJet Black:jet-black.png \nJet Black Blue Water:jet-black-blue-water.png \nJet Set:Jet-Set.png \nKalamata:kalamata.png \nKalamata-2:kalamata-2.png \nKalamata Burnt:kalamata-burnt.png \nKalamata Heathered Stripe:kalamata-heathered-stripe.png \nKalamata High Seas Kalamata Woodland:kalamata-high-seas-kalamata-woodland.png \nKalamata Pops Of Palm:kalamata-pops-of-palm.png\nKalamata Swell:kalamata-swell.png \nKalamata Tek:kalamata-tek.png \nKalamata Tek Kalamata Swell:kalamata-tek-kalamata-swell.png \nKalamata Vertical Stripe:kalamata-vertical-stripe.png \nKalamata Woodland:kalamata-woodland.png\nKhaki:khaki.png \nLarkspur:Larkspur.png \nLatigo Bay:latigo-bay.png \nLaurel Wreath:laurel-wreath.png \nLaurel Wreath Asslt:laurel-wreath-asslt.png \nLaurel Wreath Pops Of Palm Critter:laurel-wreath-pops-of-palm-critter.png \nLead:lead.png \nLettuce Green:lettuce-green.png \nLight Taupe:Light-Taupe.png \nLilac Snow:Lilac-Snow.png \nLilas:Lilas.png \nLily Pad:lily-pad.png \nLite Eco Blue:lite-eco-blue.png \nLunar Rock:lunar-rock.png \nLunar Rock Lotta Lines:lunar-rock-lotta-lines.png \nLunar Rock Water Swirls:lunar-rock-water-swirls.png\nLush: lush.png\nLyons Blue:lyons-blue.png \nLyons Blue High Seas:lyons-blue-high-seas.png \nLyons Blue M80:lyons-blue-m80.png \nLyons Blue Pops Of Palms:lyons-blue-pops-of-palms.png \nMadder Brown:Madder-Brown.png \nMahi Aop Meadowbrook:mahi-aop-meadowbrook.png\nMahi Camo:mahi-camo.png \nMahi Faded:mahi-faded.png \nMahi Green:mahi-green.png \nMalachite Green:Malachite-Green.png \nMallard Green Ceramin:mallard-green-ceramin.png \nMango:Mango.png \nMeadowbrook:meadowbrook.png \nMeadowbrook Asslt:meadowbrook-asslt.png \nMeadowbrook Cheetah Streaks:meadowbrook-cheetah-streaks.png\nMeadowbrook Euphoria:meadowbrook-euphoria.png \nMeadowbrook High Seas:meadowbrook-high-seas.png\nMeadowbrook Tek:meadowbrook-tek.png \nMeadowbrook Tek Meadowbrook Asslt:meadowbrook-tek-meadowbrook-asslt.png \nMeadowbrook Water Swirls:meadowbrook-water-swirls.png\nMeadowbrook Water Swirls Tonal:meadowbrook-water-swirls-tonal.png\nMeadow Grunge Scales:meadow-grunge-scales.png'\nMeadowbrook White Caps:meadowbrook-white-caps.png \nMedium Gray: medium-gray.png\nMilitary Green:military-green.png \nMilitary Olive:Military-Olive.png \nMilitary Olive Woodland:military-olive-woodland.png\nMilitary Olive Woodland Anthracite Woodland:military-olive-woodland-anthracite-woodland.png\nMimosa:mimosa.png \nMisty Jade:Misty-Jade.png \nMisty Rose:Misty-Rose.png \nMolten Lava Anthracite:molten-lava-anthracite.png \nMontana Grape:montana-grape.png\nMontana Grape Leaf Lines:montana-grape-leaf-lines.png\nMontana Grape Vertical Stripe:montana-grape-vertical-stripe.png \nMontana Grape Water Swirls:montana-grape-water-swirls.png \nMoonless Night:moonless-night.png \nMoonlight Jade:moonlight-jade.png \nMoonlight Ocean:moonlight-ocean.png \nMulti:Multi.png \nNavy:navy.png \nNew Wheat:new-wheat.png\nNile Grey:nile-grey.png \nOak Buff Castlerock:oak-buff-castlerock.png \nOak Buff Silver Filigree:Oak-Buff-Silver-Filigree.png \nOcean Color:Ocean-Color.png \nOcean Depth:Ocean-Depth.png \nOcean Wave:Ocean-Wave.png \nOil Blue:oil-blue.png \nOrchid Hush:Orchid-Hush.png \nOrchid Hush Tonal Floral:orchid-hush-tonal-floral.png\nOuter Space:outer-space.png \nOuter Space Lure Print:outer-space-lure-print.png \nOxblood Red:oxblood-red.png \nOxblood Red Anthracite:oxblood-red-anthracite.png \nOmphalodes:omphalodes.png\nOxblood Red Heather:oxblood-red-heather.png \nPapaya Punch:papaya-punch.png \nPastel Blue:pastel-blue.png  \nPastel Blue Water:pastel-blue-water.png \nPeach:Peach.png  \nPeaches N Cream:peaches-n-cream.png \nPeach Parfait:peach-parfait.png \nPeach Parfait High Seas:peach-parfait-high-seas.png \nPeach Parfait High Seas Glacier Gray Whitecaps:peach-parfait-high-seas-glacier-gray-whitecaps.png \nPeach Parfait Leaf Lines:peach-parfait-leaf-lines.png\nPeach Parfait Macroflora:peach-parfait-macroflora.png\nPeach Parfait Swell:peach-parfait-swell.png \nPeach Parfait Water Blocks:peach-parfait-water-blocks.png \nPeach Parfait Water Swirls:peach-parfait-water-swirls.png\nPeach Quartz:Peach-Quartz.png \nPeacock Bass:peacock-bass.png \nPink Lemonade:pink-lemonade.png \nPink wave:pink-wave.png \nPistachio Green:pistachio-green.png \nPistachio Green Rpm:pistachio-green-rpm.png \nPlacid Blue:Placid-Blue.png \nPoppy Red:poppy-red.png \nPorcelain Rose:procelain-rose.png \nPowder Blue:Powder-Blue.png \nPowder Blue 2:powder-blue-2.png \nPowder Blue Baja Stripe:powder-blue-baja-stripe.png \nPowder Blue Digi Seas:powder-blue-digi-seas.png\nPowder Blue Euphoria:powder-blue-euphoria.png\nPowder Blue Floral:powder-blue-floral.png\nPowder Blue Haze:powder-blue-haze.png \nPowder Blue Cheetah Streaks:powder-blue-cheetah-streaks.png\nPowder Blue Lotta Lines:powder-blue-lotta-lines.png \nPowder Blue Seaweed:powder-blue-seaweed.png \nPowder Blue Total Tribe  Hibiscus:powder-blue-total-tribe-hibiscus.png\nPowder Blue Total Tribe Tonal:powder-blue-total-tribe-tonal.png \nPowder Blue Water Swirls:powder-blue-water-swirls.png\nPowder Blue Whitecaps:powder-blue-whitecaps.png \nPowder Blue Brilliant White: powder-blue-brilliant-white.png\nPrairie Sunset:prairie-sunset.png \nPumice Stone:pumice-stone.png \nPurple Dove:purple-dove.png\nPurple Dove Asslt:purple-dove-asslt.png \nPurple Dove Cheetah Streaks:purple-dove-cheetah-streaks.png\nPurple Dove Floral:purple-dove-floral.png\nPurple Dove Leaf Lines:purple-dove-leaf-lines.png\nPurple Dove Lotta Lines:purple-dove-lotta-lines.png \nPurple Dove Lotta Lines Lyons Blue Pops Of Palms:purple-dove-lotta-lines-lyons-blue-pops-of-palms.png \nPurple Dove Lotta Lines Lyons Blue Pops Of Palms 3c:purple-dove-lotta-lines-lyons-blue-pops-of-palms-3c.png \nPurple Dove Macroflora:purple-dove-macroflora.png\nPurple Dove Seaweed:purple-dove-seaweed.png \nPurple Dove Shark Teeth:purple-dove-shark-teeth.png \nPurple Dove Tonal Florals:purple-dove-tonal-florals.png\nPurple Heather:Purple-Heather.png \nReal Teal:real-teal.png \nReal Teal Arcadia:real-teal-arcadia.png \nReal Teal White:real-teal-white.png \nRed Coral Grouper:red-coral-grouper.png \nRedfish:Redfish.png \nRed Violet:red-violet.png\nRed Violet Cheetah Streaks:red-violet-cheetah-streaks.png \nRed Violet High Seas:red-violet-high-seas.png\nRed Violet Water Tiger:red-violet-water-tiger.png\nRifle Green:Rifle-Green.png \nRifle Green Anthracite:rifle-green-anthracite.png \nRifle Green Heather:rifle-green-heather.png \nRobalo:robalo.png   \nRose Smoke:rose-smoke.png \nRose Smoke Bamboo:rose-smoke-bamboo.png \nRose Smoke Burnt:rose-smoke-burnt.png \nRose Smoke Lotta Lines:rose-smoke-lotta-lines.png\nRose Smoke Lush Tonal:rose-smoke-lush-tonal.png\nRose Smoke Macroflora:rose-smoke-macroflora.png \nRose Smoke Water Swirls:rose-smoke-water-swirls.png \nRoyal:royal.png \nSahara Sun:Sahara-Sun.png \nSailfish:sailfish.png \nSalmon Haze:salmon-haze.png \nSalmon Horizontal Stripe:salmon-horizontal-stripe.png\nSalmon Out Of Palms:salmon-out-of-palms.png\nSalmon Pops Of Palm Critter:salmon-pops-of-palm-critter.png \nSalmon Pops Of Palms:salmon-pops-of-palms.png \nSalmon Rose:Salmon-Rose.png \nSalmon Rose Macroflora:salmon-rose-macroflora.png \nSalmon Rose Water Blocks:salmon-rose-water-blocks.png \nSandstone:sandstone.png \nSatellite:satellite.png \nScarred Tuna:scarred-tuna.png \nScuba Blue:scuba-blue.png \nSeafoam Green:seafoam-green.png \nSea Foam Green:sea-foam-green.png \nSea Foam Green Mahi:sea-foam-green-mahi.png \nSea Fog:Sea-Fog.png   \nSeafoam:seafoam.png\nSeagrass:Seagrass.png \nSeaport:Seaport.png \nShadow:shadow.png\nShadow 4 Stripe:shadow-4-stripe.png\nShadow Asslt:shadow-asslt.png \nShadow Asslt Purple Dove M80:shadow-assault-purple-dove-m80.png \nShadow Cheetah Streaks Tonal:shadow-cheetah-streaks-tonal.png\nShadow Digi seas:shadow-digi-seas.png\nShadow Leaf Blotch:shadow-leaf-blotch.png \nShadow Lotta Lines:shadow-lotta-lines.png \nShadow Pops Of Palm:shadow-pops-of-palm.png \nShadow Seaweed:shadow-seaweed.png \nShadow Splatter Powder Blue Seaweed:shadow-splatter-powder-blue-seaweed.png \nShadow Spray:shadow-spray.png \nShadow White Caps:shadow-white-caps.png \nShell Pink:shell-pink.png \nSilver Pine: silver-pine.png\nSilver Filigree:silver-filigree.png \nSilver Filigree Oak Buff:silver-filigree-oak-buff.png \nSilver Pink:silver-pink.png \nSky Blue:Sky-Blue.png \nSkylight:skylight.png \nSkylight Blurred Leaf Lines:skylight-blurred-leaf-lines.png \nSkylight Cheetah Streaks:skylight-cheetah-streaks.png\nSkylight Little Bird Of Paradise:skylight-little-bird-of-paradise.png \nSkyway:skyway.png \nSnapdragon:snapdragon.png\nSnook:snook.png \nSnorkel Blue:snorkel-blue.png \nSnorkel Blue Shark:snorkel-blue-shark.png \nSoothing Sea:Soothing-Sea.png \nSpicy Orange:Spicy-Orange.png \nStone Blue:stone-blue.png \nStone Blue Malachite Green:stone-blue-malachite-green.png \nStonewash:Stonewash.png \nStone Wash:stone-wash.png \nStormy Seas:stormy-seas.png \nStormy Weather:stormy-weather.png \nStriper Print:Striper-Print.png \nSunburst:sunburst.png \nSun Dried Tomato:sun-dried-tomato.png \nSun Orange:sun-orange.png \nSurf Spray:surf-spray.png  \nSyrah:Syrah.png \nTeal Blue:teal-blue.png \nTea Rose:Tea-Rose.png \nTempest:Tempest.png \nTurbulence Bass:turbulence-bass.png \nTurtle Dove:turtle-dove.png \nTurtle Dove Little Bird Of Paradise:turtle-dove-little-bird-of-paradise.png \nTwilight Mauve: twilight-mauve.png\nUsa Flag:usa-flag.png \nUsa H2o Digi:usa-h2o-digi.png\nUsa Tek:usa-tek.png \nVapor Blue:Vapor-Blue.png \nVents:vents.png \nVerdant Green:verdant-green.png \nWahoo:wahoo.png\nWater Blue:water-blue.png \nWaves:waves.png \nWdlnd: wdlnd.png\nWhite:White.png \nWhite Grunge:White-Grunge.png \nWhite Water:white-water.png \nWindsome Orchid:windsome-orchid.png \nZephyr:zephyr.png",
    "show_vendor": true,
    "show_secondary_image": true,
    "product_add_to_cart": false,
    "show_product_rating": false,
    "show_discount": false,
    "discount_mode": "saving",
    "product_color_display": "swatch",
    "product_image_size": "square",
    "search_enable_blog_posts": false,
    "search_enable_collections": true,
    "search_unavailable_products": "hide",
    "cart_type": "drawer",
    "cart_empty_button_link": "shopify:\/\/collections\/all",
    "cart_show_free_shipping_threshold": true,
    "cart_free_shipping_threshold": "100",
    "social_facebook": "https:\/\/www.facebook.com\/people\/Go-Outdoor-Nation\/100089781911045\/",
    "social_instagram": "https:\/\/www.instagram.com\/_outdoornation\/",
    "social_youtube": "https:\/\/www.youtube.com\/watch?v=V6xR5EFrCXI",
    "social_tiktok": "",
    "favicon": "shopify:\/\/shop_images\/ON_Icon_3e96842f-36f9-4324-9cc6-fe03d61e460e.png",
    "checkout_sidebar_background_color": "#f5f5f5",
    "checkout_accent_color": "#282828",
    "checkout_button_color": "#405de6",
    "checkout_error_color": "#de2a2a",
    "accent_color": "#405de6",
    "scm_pl_piregex": ".flickity-viewport .product__media-item img",
    "sections": {
      "announcement-bar": {
        "type": "announcement-bar",
        "blocks": {
          "message-1": {
            "type": "message",
            "disabled": true,
            "settings": {
              "text": "LABOR DAY SALE! FREE HAT with Orders over $75.",
              "learn_more_text": "Learn More",
              "title": "",
              "content": "",
              "button_text": "",
              "button_link": ""
            }
          },
          "8894e00d-ae29-4710-9d88-270ce171a00e": {
            "type": "message",
            "settings": {
              "text": "30% Off Sitewide! Auto Applied At Checkout",
              "learn_more_text": "",
              "title": "",
              "content": "",
              "button_text": "free shipping",
              "button_link": "shopify:\/\/collections\/sale-1"
            }
          },
          "e31a6146-04bc-4da4-a594-07274b867e0b": {
            "type": "message",
            "disabled": true,
            "settings": {
              "text": "Announce something here",
              "learn_more_text": "Learn more",
              "title": "",
              "content": "",
              "button_text": "",
              "button_link": ""
            }
          },
          "8bf34c49-5412-46f8-bbd9-e3971cb8f8b8": {
            "type": "message",
            "disabled": true,
            "settings": {
              "text": "Announce something here",
              "learn_more_text": "Learn more",
              "title": "",
              "content": "",
              "button_text": "",
              "button_link": ""
            }
          }
        },
        "block_order": [
          "message-1",
          "8894e00d-ae29-4710-9d88-270ce171a00e",
          "e31a6146-04bc-4da4-a594-07274b867e0b",
          "8bf34c49-5412-46f8-bbd9-e3971cb8f8b8"
        ],
        "settings": {
          "announcement_bar_position": "sticky",
          "announcement_text_size": "normal",
          "autoplay": false,
          "cycle_speed": 5,
          "background": "#1a1818",
          "text_color": "#ffffff",
          "button_background": "#282828",
          "button_text_color": "#ffffff"
        }
      },
      "header": {
        "type": "header",
        "blocks": {
          "aa7d9fd4-a660-4392-a674-a7e689106850": {
            "type": "mega_menu",
            "settings": {
              "menu_item": "MEN",
              "images_position": "right",
              "image_1": "shopify:\/\/shop_images\/M_top-2.jpg",
              "image_1_heading": "TOPS",
              "image_1_text": "",
              "image_1_link": "shopify:\/\/collections\/all-mens-tops",
              "image_2": "shopify:\/\/shop_images\/M_bottoms-2_8cbefa46-974f-402c-b7a0-8ad0451dc7e0.jpg",
              "image_2_heading": "BOTTOMS",
              "image_2_text": "",
              "image_2_link": "shopify:\/\/collections\/mens-bottoms",
              "image_3": "shopify:\/\/shop_images\/M_Acce.jpg",
              "image_3_heading": "ACCESSORIES",
              "image_3_text": "",
              "image_3_link": "shopify:\/\/collections\/accessories",
              "image_4_heading": "",
              "image_4_text": "",
              "image_4_link": "shopify:\/\/collections\/uv-bundle",
              "image_5_heading": "",
              "image_5_text": "",
              "image_5_link": "",
              "image_6_heading": "",
              "image_6_text": "",
              "image_6_link": ""
            }
          },
          "213240a7-1134-40af-bda3-5c4434305974": {
            "type": "mega_menu",
            "settings": {
              "menu_item": "WOMEN",
              "images_position": "right",
              "image_1": "shopify:\/\/shop_images\/W_bottoms-2.jpg",
              "image_1_heading": "TOPS",
              "image_1_text": "",
              "image_1_link": "shopify:\/\/collections\/all-womens-tops",
              "image_2": "shopify:\/\/shop_images\/DSC00733.jpg",
              "image_2_heading": "BOTTOMS",
              "image_2_text": "",
              "image_2_link": "shopify:\/\/collections\/womens-bottoms",
              "image_3": "shopify:\/\/shop_images\/W_Acce.jpg",
              "image_3_heading": "ACCESSORIES",
              "image_3_text": "",
              "image_3_link": "shopify:\/\/collections\/womens-accessories",
              "image_4_heading": "",
              "image_4_text": "",
              "image_4_link": "shopify:\/\/collections\/uv-bundle",
              "image_5_heading": "",
              "image_5_text": "",
              "image_5_link": "",
              "image_6_heading": "",
              "image_6_text": "",
              "image_6_link": ""
            }
          },
          "c6b25ba5-8f7c-488f-861a-9499e562944b": {
            "type": "mega_menu",
            "settings": {
              "menu_item": "Shop by Brand",
              "images_position": "right",
              "image_1": "shopify:\/\/shop_images\/Gillz_7e3ee24c-9916-4152-9ecd-7958fe441dbd.jpg",
              "image_1_heading": "",
              "image_1_text": "",
              "image_1_link": "shopify:\/\/collections\/gillz",
              "image_2": "shopify:\/\/shop_images\/Dropdown_manu_Reel_life.jpg",
              "image_2_heading": "",
              "image_2_text": "",
              "image_2_link": "shopify:\/\/collections\/reel-life",
              "image_3": "shopify:\/\/shop_images\/Fintech_257920a5-742a-4607-a738-0e163b1f5a86.jpg",
              "image_3_heading": "",
              "image_3_text": "",
              "image_3_link": "shopify:\/\/collections\/fintech",
              "image_4": "shopify:\/\/shop_images\/mad-pelican_DD_menu_brand.jpg",
              "image_4_heading": "",
              "image_4_text": "",
              "image_4_link": "shopify:\/\/collections\/mad-pelican",
              "image_5_heading": "",
              "image_5_text": "",
              "image_5_link": "",
              "image_6_heading": "",
              "image_6_text": "",
              "image_6_link": ""
            }
          },
          "e4e1511b-2d92-49ee-ab32-bc938ec61770": {
            "type": "mega_menu",
            "settings": {
              "menu_item": "Shop by Activity",
              "images_position": "right",
              "image_1": "shopify:\/\/shop_images\/nav-beach_62f0fca4-096a-4050-861e-bf8f22819ba2.jpg",
              "image_1_heading": "Beach",
              "image_1_text": "",
              "image_1_link": "shopify:\/\/collections\/beach",
              "image_2": "shopify:\/\/shop_images\/nav-fishing_ee44eb9d-dd6c-42c2-b34c-d8608e2408de.jpg",
              "image_2_heading": "Fishing",
              "image_2_text": "",
              "image_2_link": "shopify:\/\/collections\/fishing",
              "image_3": "shopify:\/\/shop_images\/Nav_On_Site.jpg",
              "image_3_heading": "On Site",
              "image_3_text": "",
              "image_3_link": "shopify:\/\/collections\/onsite",
              "image_4": "shopify:\/\/shop_images\/Nav_Outdoor.jpg",
              "image_4_heading": "Outdoor",
              "image_4_text": "",
              "image_4_link": "shopify:\/\/collections\/outdoor",
              "image_5_heading": "Shop by Activity",
              "image_5_text": "",
              "image_5_link": "",
              "image_6_heading": "",
              "image_6_text": "",
              "image_6_link": ""
            }
          },
          "b3a80c10-d073-4268-8250-5e683fb71ee2": {
            "type": "mega_menu",
            "settings": {
              "menu_item": "Shop By Category",
              "images_position": "right",
              "image_1": "shopify:\/\/shop_images\/DSC-6.jpg",
              "image_1_heading": "MEN'S",
              "image_1_text": "",
              "image_1_link": "shopify:\/\/collections\/mens",
              "image_2": "shopify:\/\/shop_images\/DSC-5_a9ff7397-a14a-4e13-9b53-9578ed15b622.jpg",
              "image_2_heading": "WOMEN'S",
              "image_2_text": "",
              "image_2_link": "shopify:\/\/collections\/womens",
              "image_3_heading": "",
              "image_3_text": "",
              "image_3_link": "",
              "image_4_heading": "",
              "image_4_text": "",
              "image_4_link": "",
              "image_5_heading": "",
              "image_5_text": "",
              "image_5_link": "",
              "image_6_heading": "",
              "image_6_text": "",
              "image_6_link": ""
            }
          },
          "17f53520-11f0-4740-ad1f-e8926775066f": {
            "type": "mega_menu",
            "settings": {
              "menu_item": "About Us",
              "images_position": "right",
              "image_1": "shopify:\/\/shop_images\/GILLZ_63e332e1-b47f-459c-90e1-11cc034971a0.jpg",
              "image_1_heading": "Gillz",
              "image_1_text": "",
              "image_1_link": "shopify:\/\/pages\/gillz",
              "image_2": "shopify:\/\/shop_images\/ReelLife_1a253806-1d4d-40f6-83d4-0182817881e0.jpg",
              "image_2_heading": "Reel Life",
              "image_2_text": "",
              "image_2_link": "shopify:\/\/pages\/reel-life",
              "image_3": "shopify:\/\/shop_images\/Fintech_48a28582-ac59-48aa-85d0-4b5267e4ff0e.jpg",
              "image_3_heading": "Fintech",
              "image_3_text": "",
              "image_3_link": "shopify:\/\/pages\/fintech",
              "image_4": "shopify:\/\/shop_images\/mad-pelican_DD_menu.jpg",
              "image_4_heading": "Mad Pelican",
              "image_4_text": "",
              "image_4_link": "shopify:\/\/pages\/mad-pelican",
              "image_5_heading": "",
              "image_5_text": "",
              "image_5_link": "",
              "image_6_heading": "",
              "image_6_text": "",
              "image_6_link": ""
            }
          },
          "be77e5c1-75d3-487e-91ed-df514dc64a16": {
            "type": "mega_menu",
            "settings": {
              "menu_item": "Sale",
              "images_position": "right",
              "image_1_heading": "",
              "image_1_text": "",
              "image_1_link": "shopify:\/\/collections\/uv-bundle",
              "image_2": "shopify:\/\/shop_images\/Closeout_sales_bae75c66-53c8-44d8-9438-6c6fd8d03734.jpg",
              "image_2_heading": "CLOSEOUT SALE",
              "image_2_text": "",
              "image_2_link": "shopify:\/\/collections\/sale-1",
              "image_3_heading": "",
              "image_3_text": "",
              "image_3_link": "",
              "image_4_heading": "",
              "image_4_text": "",
              "image_4_link": "",
              "image_5_heading": "",
              "image_5_text": "",
              "image_5_link": "",
              "image_6_heading": "",
              "image_6_text": "",
              "image_6_link": ""
            }
          }
        },
        "block_order": [
          "aa7d9fd4-a660-4392-a674-a7e689106850",
          "213240a7-1134-40af-bda3-5c4434305974",
          "c6b25ba5-8f7c-488f-861a-9499e562944b",
          "e4e1511b-2d92-49ee-ab32-bc938ec61770",
          "b3a80c10-d073-4268-8250-5e683fb71ee2",
          "17f53520-11f0-4740-ad1f-e8926775066f",
          "be77e5c1-75d3-487e-91ed-df514dc64a16"
        ],
        "settings": {
          "enable_sticky_header": true,
          "logo": "shopify:\/\/shop_images\/ON_Logo_355x-01-2x.png",
          "logo_max_width": 250,
          "mobile_logo_max_width": 150,
          "navigation_menu": "main-menu",
          "sidebar_navigation_menu": "main-menu",
          "header_layout": "logo_left_navigation_center",
          "show_icons": true,
          "reduce_desktop_padding": true,
          "show_locale_selector": true,
          "show_country_selector": false,
          "enable_transparent_header": false,
          "transparent_header_text_color": "#ffffff",
          "search_menu": "main-menu"
        }
      },
      "footer": {
        "type": "footer",
        "blocks": {
          "44a3c877-8756-40eb-83ea-30d3b3acaa3e": {
            "type": "image",
            "settings": {
              "image": "shopify:\/\/shop_images\/Logo-ON-footer.svg",
              "image_width": 140
            }
          },
          "links": {
            "type": "links",
            "settings": {
              "menu": "footer"
            }
          },
          "695708e5-802b-4d0d-a9bf-2868c2bba26e": {
            "type": "links",
            "settings": {
              "menu": "shop-all"
            }
          },
          "034eb974-8714-4a32-ba21-4c1fdd54fd41": {
            "type": "links",
            "settings": {
              "menu": ""
            }
          },
          "b0257441-79c4-4d6d-913d-1be810a0d0cb": {
            "type": "links",
            "settings": {
              "menu": "resources"
            }
          },
          "634fba70-4212-4bbd-a25b-5354da704247": {
            "type": "social_media",
            "settings": {
              "title": "Follow us",
              "content": ""
            }
          }
        },
        "block_order": [
          "44a3c877-8756-40eb-83ea-30d3b3acaa3e",
          "links",
          "695708e5-802b-4d0d-a9bf-2868c2bba26e",
          "034eb974-8714-4a32-ba21-4c1fdd54fd41",
          "b0257441-79c4-4d6d-913d-1be810a0d0cb",
          "634fba70-4212-4bbd-a25b-5354da704247"
        ],
        "settings": {
          "show_payment_icons": true,
          "show_country_selector": false,
          "show_locale_selector": true,
          "show_cookie_bar": false,
          "cookie_bar_title": "Cookie policy",
          "cookie_bar_content": "<p>I agree to the processing of my data in accordance with the conditions set out in the policy of Privacy.<\/p>"
        }
      },
      "popup": {
        "type": "popup",
        "settings": {
          "enable": false,
          "apparition_delay": 5,
          "show_only_on_index": true,
          "show_only_for_visitors": true,
          "show_only_once": true,
          "image_position": "left",
          "title": "Get 10% off",
          "content": "<p>Promotions, new products and sales. Directly to your inbox.<\/p>"
        }
      },
      "mini-cart": {
        "type": "mini-cart",
        "settings": {
          "show_order_note": true,
          "show_checkout_button": true,
          "empty_button_link": "\/",
          "show_recommendations": true,
          "recommendations_title": "You may also like"
        }
      },
      "static-text-with-icons": {
        "type": "static-text-with-icons",
        "blocks": {
          "static-text-with-icons-0": {
            "type": "item",
            "settings": {
              "icon": "picto-box",
              "custom_icon_width": 50,
              "title": "Free shipping",
              "content": "<p>Free worldwide shipping and returns - customs and duties taxes included<\/p>"
            }
          },
          "static-text-with-icons-1": {
            "type": "item",
            "settings": {
              "icon": "picto-phone",
              "custom_icon_width": 50,
              "title": "Customer service",
              "content": "<p>We are available from monday to friday to answer your questions.<\/p>"
            }
          },
          "static-text-with-icons-2": {
            "type": "item",
            "settings": {
              "icon": "picto-lock",
              "custom_icon_width": 50,
              "title": "Secure payment",
              "content": "<p>Your payment information is processed securely.<\/p>"
            }
          },
          "static-text-with-icons-3": {
            "type": "item",
            "settings": {
              "icon": "picto-email",
              "custom_icon_width": 50,
              "title": "Contact us",
              "content": "<p>Need to contact us ? Just send us an e-mail at info@yourstore.com<\/p>"
            }
          }
        },
        "block_order": [
          "static-text-with-icons-0",
          "static-text-with-icons-1",
          "static-text-with-icons-2",
          "static-text-with-icons-3"
        ],
        "settings": {
          "show_section": false,
          "background": "rgba(0,0,0,0)",
          "text_color": "rgba(0,0,0,0)"
        }
      },
      "static-newsletter": {
        "type": "static-newsletter",
        "settings": {
          "show_section": false,
          "reveal_on_scroll": true,
          "image": "shopify:\/\/shop_images\/SUBSCRIBE_banner_1_2.jpg",
          "subheading": "Subscribe to get exclusive offers",
          "content": "<p>Promotions, new products and sales. Directly to your inbox.<\/p>",
          "text_position": "left",
          "text_alignment": "left",
          "text_background": "rgba(0,0,0,0)",
          "text_color": "rgba(0,0,0,0)",
          "button_background": "#f06a22",
          "button_text_color": "rgba(0,0,0,0)"
        }
      },
      "header-wholesale": {
        "type": "header-wholesale",
        "blocks": {
          "da3f52da-c813-4272-bb34-a99cd5209937": {
            "type": "mega_menu",
            "settings": {
              "menu_item": "Shop By Brand",
              "images_position": "right",
              "image_1": "shopify:\/\/shop_images\/Gillz_e6d2b35c-8cc6-4c00-bed0-be53a6801c64.jpg",
              "image_1_heading": "",
              "image_1_text": "",
              "image_1_link": "https:\/\/outdoornation.com\/collections\/order-form?sort_by=title-ascending&filter.p.vendor=Gillz&filter.v.price.gte=&filter.v.price.lte=",
              "image_2": "shopify:\/\/shop_images\/ReelLife_75c57264-bcdc-4b60-b226-e9315492889c.jpg",
              "image_2_heading": "",
              "image_2_text": "",
              "image_2_link": "https:\/\/outdoornation.com\/collections\/order-form?sort_by=title-ascending&filter.p.vendor=Reel+Life&filter.v.price.gte=&filter.v.price.lte=",
              "image_3": "shopify:\/\/shop_images\/Fintech_51f79d9f-fcb2-4753-a011-7c6785230e0e.jpg",
              "image_3_heading": "",
              "image_3_text": "",
              "image_3_link": "https:\/\/outdoornation.com\/collections\/order-form?sort_by=title-ascending&filter.p.vendor=Fintech&filter.v.price.gte=&filter.v.price.lte=",
              "image_4": "shopify:\/\/shop_images\/MadPelican_339ff002-3cd3-4eca-9c8f-16fa0d621e3a.jpg",
              "image_4_heading": "",
              "image_4_text": "",
              "image_4_link": "https:\/\/outdoornation.com\/collections\/order-form?sort_by=title-ascending",
              "image_5_heading": "",
              "image_5_text": "",
              "image_5_link": "",
              "image_6_heading": "",
              "image_6_text": "",
              "image_6_link": ""
            }
          },
          "4c8ad157-214a-4e3a-9c85-1a32444b300f": {
            "type": "mega_menu",
            "settings": {
              "menu_item": "Shop By Category",
              "images_position": "right",
              "image_1": "shopify:\/\/shop_images\/DSC-6_b873d0af-5479-4627-b90f-f6dc6c261d48.jpg",
              "image_1_heading": "Men's",
              "image_1_text": "",
              "image_1_link": "https:\/\/outdoornation.com\/collections\/order-form?sort_by=best-selling&filter.v.price.gte=&filter.v.price.lte=&filter.p.tag=Mens",
              "image_2": "shopify:\/\/shop_images\/DSC-5_a9ff7397-a14a-4e13-9b53-9578ed15b622.jpg",
              "image_2_heading": "Women's",
              "image_2_text": "",
              "image_2_link": "https:\/\/outdoornation.com\/collections\/order-form?sort_by=best-selling&filter.v.price.gte=&filter.v.price.lte=&filter.p.tag=Womens",
              "image_3_heading": "",
              "image_3_text": "",
              "image_3_link": "",
              "image_4_heading": "",
              "image_4_text": "",
              "image_4_link": "",
              "image_5_heading": "",
              "image_5_text": "",
              "image_5_link": "",
              "image_6_heading": "",
              "image_6_text": "",
              "image_6_link": ""
            }
          },
          "aa1d5c5b-8c8a-47ab-b4b7-1334ca470977": {
            "type": "mega_menu",
            "settings": {
              "menu_item": "SHOP BY ACTIVITY",
              "images_position": "right",
              "image_1": "shopify:\/\/shop_images\/nav-beach_6bc284fd-0289-4d7c-9769-6c4dfa19f896.jpg",
              "image_1_heading": "BEACH",
              "image_1_text": "",
              "image_1_link": "shopify:\/\/collections\/beach-wholesale",
              "image_2": "shopify:\/\/shop_images\/nav-fishing_465da0e1-63a8-409e-b4db-1d4b544fb562.jpg",
              "image_2_heading": "FISHING",
              "image_2_text": "",
              "image_2_link": "shopify:\/\/collections\/fishing-wholesale",
              "image_3": "shopify:\/\/shop_images\/Nav_On_Site_acf8cea8-fec6-4d8f-adc9-2aeb21aaff70.jpg",
              "image_3_heading": "ON SITE",
              "image_3_text": "",
              "image_3_link": "shopify:\/\/collections\/on-site-wholesale",
              "image_4": "shopify:\/\/shop_images\/Nav_Outdoor_edfb04d9-a19f-4b01-89c0-e92b945d6021.jpg",
              "image_4_heading": "OUTDOOR",
              "image_4_text": "",
              "image_4_link": "shopify:\/\/collections\/outdoor-wholesale",
              "image_5_heading": "",
              "image_5_text": "",
              "image_5_link": "",
              "image_6_heading": "",
              "image_6_text": "",
              "image_6_link": ""
            }
          }
        },
        "block_order": [
          "da3f52da-c813-4272-bb34-a99cd5209937",
          "4c8ad157-214a-4e3a-9c85-1a32444b300f",
          "aa1d5c5b-8c8a-47ab-b4b7-1334ca470977"
        ],
        "settings": {
          "enable_sticky_header": true,
          "logo_max_width": 140,
          "mobile_logo_max_width": 100,
          "navigation_menu": "wholesale-main-menu",
          "sidebar_navigation_menu": "",
          "header_layout": "logo_left_navigation_inline",
          "show_icons": true,
          "reduce_desktop_padding": false,
          "show_locale_selector": true,
          "show_country_selector": false,
          "enable_transparent_header": false,
          "transparent_header_text_color": "#ffffff",
          "search_menu": ""
        }
      },
      "footer-wholesale": {
        "type": "footer-wholesale",
        "blocks": {
          "6152c47e-8027-440d-8c25-2a6d6e66cf0f": {
            "type": "image",
            "settings": {
              "image": "shopify:\/\/shop_images\/ON_Logo.svg",
              "image_width": 300
            }
          },
          "54b8e4fd-5b04-4107-8fa5-53f1ef2b9b90": {
            "type": "links",
            "disabled": true,
            "settings": {
              "menu": "footer"
            }
          },
          "042d4f00-4a42-4d02-a333-24a3bcd1e4d2": {
            "type": "text",
            "disabled": true,
            "settings": {
              "title": "About our store",
              "content": "<p>Use this text area to tell your customers about your brand and vision. You can change it in the theme editor.<\/p>"
            }
          },
          "footer-wholesale-3": {
            "type": "social_media",
            "settings": {
              "title": "Follow Us",
              "content": ""
            }
          }
        },
        "block_order": [
          "6152c47e-8027-440d-8c25-2a6d6e66cf0f",
          "54b8e4fd-5b04-4107-8fa5-53f1ef2b9b90",
          "042d4f00-4a42-4d02-a333-24a3bcd1e4d2",
          "footer-wholesale-3"
        ],
        "settings": {
          "show_payment_icons": true,
          "show_country_selector": true,
          "show_locale_selector": true,
          "show_cookie_bar": false,
          "cookie_bar_title": "Cookie policy",
          "cookie_bar_content": "<p>I agree to the processing of my data in accordance with the conditions set out in the policy of Privacy.<\/p>"
        }
      }
    },
    "content_for_index": [

    ],
    "blocks": {
      "733389323033596483": {
        "type": "shopify:\/\/apps\/okendo-product-reviews-ugc\/blocks\/theme-settings\/bb689e69-ea70-4661-8fb7-ad24a2e23c29",
        "disabled": false,
        "settings": {
          "show_preview_data": false
        }
      },
      "15885745614559378752": {
        "type": "shopify:\/\/apps\/accessibly\/blocks\/app-embed\/4b59303e-1141-4c8a-945f-bf4adb516864",
        "disabled": false,
        "settings": {
          "themeColor": "#574CD5",
          "iconColor": "#574CD5",
          "showLogo": true,
          "topBottomPosition": 10,
          "rightLeftPosition": 10,
          "iconSize": "small",
          "iconCustomSize": 64,
          "position": "middle-right"
        }
      },
      "855628211100114053": {
        "type": "shopify:\/\/apps\/klaviyo-email-marketing-sms\/blocks\/klaviyo-onsite-embed\/2632fe16-c075-4321-a88b-50b567f42507",
        "disabled": false,
        "settings": {
        }
      },
      "12657775114333427046": {
        "type": "shopify:\/\/apps\/essential-countdown-timer-bar\/blocks\/app_embed\/722378e8-5a70-4eae-aa89-9e44e8e9f6de",
        "disabled": false,
        "settings": {
        }
      }
    }
  },
  "presets": {
    "Carbon": {
      "button_border_radius": 0,
      "block_border_radius": "none",
      "heading_color": "#282828",
      "text_color": "#282828",
      "secondary_background": "#f5f5f5",
      "success_color": "#2e9e7b",
      "error_color": "#de2a2a",
      "header_background": "#282828",
      "footer_background": "#282828",
      "footer_text_color": "#ffffff",
      "primary_button_background": "#405de6",
      "secondary_button_background": "#f3ff34",
      "secondary_button_text_color": "#282828",
      "product_on_sale_accent": "#de2a2a",
      "product_custom_label_background": "#405de6",
      "product_custom_label_2_background": "#f3ff34",
      "product_in_stock_text_color": "#2e9e7b",
      "product_low_stock_text_color": "#de2a2a",
      "heading_font": "zurich_extended_n8",
      "heading_font_size": "medium",
      "heading_text_transform": "uppercase",
      "text_font": "zurich_n4",
      "text_font_size": 15,
      "currency_code_enabled": false,
      "stagger_products_apparition": true,
      "round_color_swatches": false,
      "show_vendor": false,
      "show_secondary_image": true,
      "product_color_display": "count",
      "product_image_size": "natural",
      "show_product_rating": false,
      "cart_type": "message",
      "cart_show_free_shipping_threshold": true,
      "accent_color": "#405de6",
      "checkout_sidebar_background_color": "#f5f5f5",
      "checkout_accent_color": "#282828",
      "checkout_button_color": "#405de6",
      "checkout_error_color": "#de2a2a",
      "sections": {
        "announcement-bar": {
          "type": "announcement-bar",
          "blocks": {
            "message-1": {
              "type": "message",
              "settings": {
              }
            }
          },
          "block_order": [
            "message-1"
          ],
          "settings": {
            "announcement_bar_position": "non_sticky",
            "announcement_text_size": "normal",
            "autoplay": true,
            "cycle_speed": 5,
            "background": "#f3ff34",
            "text_color": "#282828",
            "button_background": "#282828",
            "button_text_color": "#ffffff"
          }
        },
        "header": {
          "type": "header",
          "settings": {
            "enable_sticky_header": true,
            "navigation_menu": "main-menu",
            "header_layout": "logo_left_navigation_center",
            "show_icons": false,
            "reduce_desktop_padding": false,
            "enable_transparent_header": false,
            "transparent_header_text_color": "#ffffff"
          }
        },
        "footer": {
          "type": "footer",
          "blocks": {
            "text": {
              "type": "text",
              "settings": {
              }
            },
            "links": {
              "type": "links",
              "settings": {
                "menu": "footer"
              }
            },
            "newsletter": {
              "type": "newsletter",
              "settings": {
              }
            },
            "social_media": {
              "type": "social_media",
              "settings": {
              }
            }
          },
          "block_order": [
            "text",
            "links",
            "newsletter",
            "social_media"
          ],
          "settings": {
          }
        }
      }
    },
    "Ivory": {
      "button_border_radius": 4,
      "block_border_radius": "small",
      "heading_color": "#1a1a1a",
      "text_color": "#1a1a1a",
      "secondary_background": "#f5f1ec",
      "success_color": "#2e9e7b",
      "error_color": "#de2a2a",
      "header_background": "#56112a",
      "header_text_color": "#ffffff",
      "footer_background": "#56112a",
      "footer_text_color": "#ffffff",
      "primary_button_background": "#56112a",
      "primary_button_text_color": "#ffffff",
      "secondary_button_background": "#f7aea6",
      "secondary_button_text_color": "#56112a",
      "product_on_sale_accent": "#913b59",
      "product_custom_label_background": "#405de6",
      "product_custom_label_2_background": "#f3e5b6",
      "product_in_stock_text_color": "#2e9e7b",
      "product_low_stock_text_color": "#de2a2a",
      "heading_font": "itc_caslon_no_224_n5",
      "heading_font_size": "medium",
      "heading_text_transform": "normal",
      "text_font": "avenir_next_n4",
      "text_font_size": 15,
      "stagger_products_apparition": true,
      "round_color_swatches": true,
      "show_vendor": false,
      "show_secondary_image": true,
      "product_color_display": "count",
      "product_image_size": "natural",
      "cart_type": "drawer",
      "accent_color": "#405de6",
      "checkout_sidebar_background_color": "#f6f3ed",
      "checkout_accent_color": "#353535",
      "checkout_button_color": "#353535",
      "checkout_error_color": "#de2a2a",
      "sections": {
        "announcement-bar": {
          "type": "announcement-bar",
          "blocks": {
            "message-1": {
              "type": "message",
              "settings": {
              }
            }
          },
          "block_order": [
            "message-1"
          ],
          "settings": {
            "announcement_bar_position": "non_sticky",
            "announcement_text_size": "small",
            "autoplay": true,
            "cycle_speed": 5,
            "background": "#f7aea6",
            "text_color": "#56112a",
            "button_background": "#56112a",
            "button_text_color": "#ffffff"
          }
        },
        "header": {
          "type": "header",
          "settings": {
            "enable_sticky_header": true,
            "navigation_menu": "main-menu",
            "header_layout": "logo_center_navigation_inline",
            "show_icons": false,
            "reduce_desktop_padding": false,
            "enable_transparent_header": false,
            "transparent_header_text_color": "#ffffff"
          }
        },
        "footer": {
          "type": "footer",
          "blocks": {
            "text": {
              "type": "text",
              "settings": {
              }
            },
            "links": {
              "type": "links",
              "settings": {
                "menu": "footer"
              }
            },
            "newsletter": {
              "type": "newsletter",
              "settings": {
              }
            },
            "social_media": {
              "type": "social_media",
              "settings": {
              }
            }
          },
          "block_order": [
            "text",
            "links",
            "newsletter",
            "social_media"
          ],
          "settings": {
          }
        }
      }
    },
    "Quartz": {
      "icon_stroke_width": 1.3,
      "button_border_radius": 0,
      "block_border_radius": "none",
      "vertical_spacing": "medium",
      "heading_color": "#0d0d0d",
      "text_color": "#2e2e2e",
      "background": "#ffffff",
      "secondary_background": "#f5f5f5",
      "success_color": "#3c6e71",
      "error_color": "#de2a2a",
      "header_background": "#ffffff",
      "header_text_color": "#2e2e2e",
      "footer_background": "#ffffff",
      "footer_text_color": "#2e2e2e",
      "primary_button_background": "#051e38",
      "primary_button_text_color": "#ffffff",
      "secondary_button_background": "#dfdfdf",
      "secondary_button_text_color": "#2e2e2e",
      "product_on_sale_accent": "#de2b2b",
      "product_sold_out_accent": "#5b5b5b",
      "product_custom_label_background": "#051e38",
      "product_custom_label_2_background": "#2e9e7b",
      "product_in_stock_text_color": "#2e9e7b",
      "product_low_stock_text_color": "#de2b2b",
      "heading_font": "futura_n3",
      "heading_font_size": "medium",
      "heading_text_transform": "uppercase",
      "text_font": "din_next_n4",
      "text_font_size": 15,
      "stagger_products_apparition": true,
      "round_color_swatches": false,
      "show_vendor": false,
      "show_secondary_image": true,
      "product_color_display": "hide",
      "product_image_size": "natural",
      "cart_type": "drawer",
      "cart_icon": "tote_bag",
      "checkout_sidebar_background_color": "#f5f5f5",
      "checkout_accent_color": "#051e38",
      "checkout_button_color": "#051e38",
      "checkout_error_color": "#de2a2a",
      "accent_color": "#405de6",
      "sections": {
        "announcement-bar": {
          "type": "announcement-bar",
          "blocks": {
            "message-1": {
              "type": "message",
              "settings": {
              }
            }
          },
          "block_order": [
            "message-1"
          ],
          "settings": {
            "announcement_bar_position": "non_sticky",
            "announcement_text_size": "small",
            "autoplay": true,
            "cycle_speed": 5,
            "background": "#051e38",
            "text_color": "#ffffff",
            "button_background": "#ffffff",
            "button_text_color": "#051e38"
          }
        },
        "header": {
          "type": "header",
          "settings": {
            "enable_sticky_header": true,
            "navigation_menu": "main-menu",
            "header_layout": "logo_center_navigation_inline",
            "show_icons": true,
            "reduce_desktop_padding": false,
            "enable_transparent_header": true,
            "transparent_header_text_color": "#ffffff"
          }
        },
        "footer": {
          "type": "footer",
          "blocks": {
            "text": {
              "type": "text",
              "settings": {
              }
            },
            "links": {
              "type": "links",
              "settings": {
                "menu": "footer"
              }
            },
            "newsletter": {
              "type": "newsletter",
              "settings": {
              }
            },
            "social_media": {
              "type": "social_media",
              "settings": {
              }
            }
          },
          "block_order": [
            "text",
            "links",
            "newsletter",
            "social_media"
          ],
          "settings": {
          }
        }
      }
    },
    "Sapphire": {
      "icon_stroke_width": 1.2,
      "button_border_radius": 0,
      "block_border_radius": "none",
      "heading_color": "#0c1b54",
      "text_color": "#0c1b54",
      "background": "#ffffff",
      "secondary_background": "#f7f7f7",
      "success_color": "#708a7d",
      "error_color": "#d2545a",
      "header_background": "#0c1b54",
      "footer_background": "#0c1b54",
      "footer_text_color": "#ffffff",
      "primary_button_background": "#0c1b54",
      "secondary_button_background": "#f7f7f7",
      "secondary_button_text_color": "#0c1b54",
      "product_rating_color": "#a48156",
      "product_on_sale_accent": "#d2545a",
      "product_custom_label_background": "#405de6",
      "product_custom_label_2_background": "#f3ff34",
      "product_in_stock_text_color": "#2e9e7b",
      "product_low_stock_text_color": "#d2545a",
      "heading_font": "chong_modern_n4",
      "heading_font_size": "large",
      "heading_text_transform": "normal",
      "text_font": "trade_gothic_n4",
      "text_font_size": 15,
      "stagger_products_apparition": true,
      "round_color_swatches": true,
      "show_vendor": true,
      "show_secondary_image": true,
      "show_product_rating": true,
      "product_color_display": "hide",
      "product_image_size": "natural",
      "cart_type": "message",
      "checkout_sidebar_background_color": "#f5f5f5",
      "checkout_accent_color": "#282828",
      "checkout_button_color": "#405de6",
      "checkout_error_color": "#de2a2a",
      "accent_color": "#405de6",
      "sections": {
        "announcement-bar": {
          "type": "announcement-bar",
          "blocks": {
            "message-1": {
              "type": "message",
              "settings": {
              }
            }
          },
          "block_order": [
            "message-1"
          ],
          "settings": {
            "announcement_bar_position": "non_sticky",
            "announcement_text_size": "small",
            "autoplay": true,
            "cycle_speed": 5,
            "background": "#ffe5db",
            "text_color": "#0c1b54",
            "button_background": "#0c1b54",
            "button_text_color": "#ffffff"
          }
        },
        "header": {
          "type": "header",
          "settings": {
            "enable_sticky_header": true,
            "navigation_menu": "main-menu",
            "header_layout": "logo_center_navigation_inline",
            "show_icons": true,
            "reduce_desktop_padding": false,
            "enable_transparent_header": true,
            "transparent_header_text_color": "#ffffff"
          }
        },
        "footer": {
          "type": "footer",
          "blocks": {
            "text": {
              "type": "text",
              "settings": {
              }
            },
            "links": {
              "type": "links",
              "settings": {
                "menu": "footer"
              }
            },
            "newsletter": {
              "type": "newsletter",
              "settings": {
              }
            },
            "social_media": {
              "type": "social_media",
              "settings": {
              }
            }
          },
          "block_order": [
            "text",
            "links",
            "newsletter",
            "social_media"
          ],
          "settings": {
          }
        }
      }
    }
  }
}
